Flask_ImageAlchemy-0.0.6.dist-info/DESCRIPTION.rst
Flask_ImageAlchemy-0.0.6.dist-info/METADATA
Flask_ImageAlchemy-0.0.6.dist-info/RECORD
Flask_ImageAlchemy-0.0.6.dist-info/WHEEL
Flask_ImageAlchemy-0.0.6.dist-info/metadata.json
Flask_ImageAlchemy-0.0.6.dist-info/top_level.txt
flask_image_alchemy/__init__.py
flask_image_alchemy/admin.py
flask_image_alchemy/fields.py
flask_image_alchemy/utils.py
flask_image_alchemy/storages/__init__.py
flask_image_alchemy/storages/base.py
flask_image_alchemy/storages/file.py
flask_image_alchemy/storages/s3.py
